{"file:///c%3A/Users/smm/Desktop/mern%20social/react-social/src/pages/profile/Profile.jsx":{"language":"JavaScript JSX","code":45,"comment":0,"blank":8},"file:///c%3A/Users/smm/Desktop/mern%20social/react-social/src/pages/profile/profile.css":{"language":"CSS","code":42,"comment":0,"blank":0},"file:///c%3A/Users/smm/Desktop/mern%20social/react-social/src/index.js":{"language":"JavaScript","code":12,"comment":0,"blank":2},"file:///c%3A/Users/smm/Desktop/mern%20social/react-social/src/context/AuthReducer.js":{"language":"JavaScript","code":25,"comment":0,"blank":0},"file:///c%3A/Users/smm/Desktop/mern%20social/react-social/src/dummyData.js":{"language":"JavaScript","code":138,"comment":0,"blank":2},"file:///c%3A/Users/smm/Desktop/mern%20social/react-social/src/context/AuthContext.js":{"language":"JavaScript","code":32,"comment":0,"blank":4},"file:///c%3A/Users/smm/Desktop/mern%20social/react-social/src/context/AuthActions.js":{"language":"JavaScript","code":10,"comment":1,"blank":1},"file:///c%3A/Users/smm/Desktop/mern%20social/react-social/src/components/topbar/Topbar.jsx":{"language":"JavaScript JSX","code":62,"comment":0,"blank":3},"file:///c%3A/Users/smm/Desktop/mern%20social/react-social/src/components/topbar/topbar.css":{"language":"CSS","code":83,"comment":0,"blank":4},"file:///c%3A/Users/smm/Desktop/mern%20social/react-social/src/pages/register/Register.jsx":{"language":"JavaScript JSX","code":53,"comment":0,"blank":7},"file:///c%3A/Users/smm/Desktop/mern%20social/react-social/src/pages/register/register.css":{"language":"CSS","code":75,"comment":0,"blank":10},"file:///c%3A/Users/smm/Desktop/mern%20social/react-social/src/components/sidebar/Sidebar.jsx":{"language":"JavaScript JSX","code":66,"comment":0,"blank":3},"file:///c%3A/Users/smm/Desktop/mern%20social/react-social/src/components/sidebar/sidebar.css":{"language":"CSS","code":44,"comment":0,"blank":1},"file:///c%3A/Users/smm/Desktop/mern%20social/react-social/src/pages/register/This%20is%20a%20special%20code%20that%20helps%20make%20d.js":{"language":"JavaScript","code":7,"comment":0,"blank":1},"file:///c%3A/Users/smm/Desktop/mern%20social/react-social/src/components/share/Share.jsx":{"language":"JavaScript JSX","code":79,"comment":7,"blank":5},"file:///c%3A/Users/smm/Desktop/mern%20social/react-social/src/components/share/share.css":{"language":"CSS","code":64,"comment":1,"blank":0},"file:///c%3A/Users/smm/Desktop/mern%20social/react-social/src/pages/register/Untitled-1.js":{"language":"JavaScript","code":28,"comment":0,"blank":3},"file:///c%3A/Users/smm/Desktop/mern%20social/react-social/src/components/rightbar/rightbar.css":{"language":"CSS","code":69,"comment":0,"blank":2},"file:///c%3A/Users/smm/Desktop/mern%20social/react-social/src/components/rightbar/Rightbar.jsx":{"language":"JavaScript JSX","code":81,"comment":0,"blank":6},"file:///c%3A/Users/smm/Desktop/mern%20social/react-social/src/pages/login/Login.jsx":{"language":"JavaScript JSX","code":48,"comment":15,"blank":7},"file:///c%3A/Users/smm/Desktop/mern%20social/react-social/src/pages/login/login.css":{"language":"CSS","code":92,"comment":6,"blank":12},"file:///c%3A/Users/smm/Desktop/mern%20social/react-social/src/components/online/Online.jsx":{"language":"JavaScript JSX","code":15,"comment":0,"blank":3},"file:///c%3A/Users/smm/Desktop/mern%20social/react-social/src/components/post/Post.jsx":{"language":"JavaScript JSX","code":83,"comment":1,"blank":8},"file:///c%3A/Users/smm/Desktop/mern%20social/react-social/src/components/post/post.css":{"language":"CSS","code":65,"comment":0,"blank":0},"file:///c%3A/Users/smm/Desktop/mern%20social/react-social/src/components/online/online.css":{"language":"CSS","code":28,"comment":0,"blank":0},"file:///c%3A/Users/smm/Desktop/mern%20social/react-social/src/App.js":{"language":"JavaScript","code":30,"comment":0,"blank":8},"file:///c%3A/Users/smm/Desktop/mern%20social/react-social/src/components/feed/feed.css":{"language":"CSS","code":6,"comment":0,"blank":0},"file:///c%3A/Users/smm/Desktop/mern%20social/react-social/src/components/closeFriend/closeFriend.css":{"language":"CSS","code":12,"comment":0,"blank":0},"file:///c%3A/Users/smm/Desktop/mern%20social/react-social/src/components/closeFriend/CloseFriend.jsx":{"language":"JavaScript JSX","code":11,"comment":0,"blank":2},"file:///c%3A/Users/smm/Desktop/mern%20social/react-social/src/apiCalls.js":{"language":"JavaScript","code":10,"comment":0,"blank":1},"file:///c%3A/Users/smm/Desktop/mern%20social/react-social/README.md":{"language":"Markdown","code":38,"comment":0,"blank":33},"file:///c%3A/Users/smm/Desktop/mern%20social/react-social/src/components/feed/Feed.jsx":{"language":"JavaScript JSX","code":32,"comment":1,"blank":4},"file:///c%3A/Users/smm/Desktop/mern%20social/react-social/package.json":{"language":"JSON","code":45,"comment":0,"blank":1},"file:///c%3A/Users/smm/Desktop/mern%20social/react-social/package-lock.json":{"language":"JSON","code":16945,"comment":0,"blank":1},"file:///c%3A/Users/smm/Desktop/mern%20social/react-social/public/index.html":{"language":"HTML","code":19,"comment":0,"blank":4},"file:///c%3A/Users/smm/Desktop/mern%20social/react-social/public/assets/style.css":{"language":"CSS","code":4,"comment":0,"blank":0},"file:///c%3A/Users/smm/Desktop/mern%20social/react-social/src/pages/home/Home.jsx":{"language":"JavaScript JSX","code":18,"comment":0,"blank":3},"file:///c%3A/Users/smm/Desktop/mern%20social/react-social/src/pages/home/home.css":{"language":"CSS","code":4,"comment":0,"blank":0},"file:///c%3A/Users/smm/Desktop/mern%20social/react-social/.env":{"language":"Properties","code":1,"comment":0,"blank":0}}